monogatari/__init__.py
monogatari/data/J-MFD_2018.dic
monogatari/data/MFD.dic
monogatari/dict_counter.py
monogatari/dict_handler.py
monogatari/jmfd_counter.py
monogatari/mfd_counter.py
monogatari-2.1.1.dist-info/LICENSE
monogatari-2.1.1.dist-info/METADATA
monogatari-2.1.1.dist-info/WHEEL
monogatari-2.1.1.dist-info/RECORD
