Metadata-Version: 2.1
Name: Monogatari
Version: 2.1.1
Summary: Generates word statistics
License: MIT
Author: Bruno Toshio Sugano
Author-email: brunotoshio@gmail.com
Requires-Python: >=3.8,<4.0
Classifier: License :: OSI Approved :: MIT License
Classifier: Programming Language :: Python :: 3
Classifier: Programming Language :: Python :: 3.8
Classifier: Programming Language :: Python :: 3.9
Classifier: Programming Language :: Python :: 3.10
Classifier: Programming Language :: Python :: 3.11
